endofactory/__init__.py
endofactory/cli.py
endofactory/config.py
endofactory/core.py
endofactory/yaml_loader.py
endofactory-0.1.4.dist-info/METADATA
endofactory-0.1.4.dist-info/WHEEL
endofactory-0.1.4.dist-info/entry_points.txt
endofactory-0.1.4.dist-info/RECORD
