Metadata-Version: 2.3
Name: endofactory
Version: 0.1.4
Summary: Revolutionary EndoVQA dataset construction tool for rapid dataset mixing and configuration
License: MIT
Keywords: endoscopy,medical,VQA,dataset,polars,yaml,cli
Author: TiramisuQiao
Author-email: tlmsq@outlook.com
Requires-Python: >=3.9
Classifier: Programming Language :: Python :: 3
Classifier: License :: OSI Approved :: MIT License
Classifier: Operating System :: OS Independent
Classifier: Topic :: Scientific/Engineering :: Artificial Intelligence
Classifier: Topic :: Scientific/Engineering :: Information Analysis
Provides-Extra: tests
Requires-Dist: pillow (>=10.0.0)
Requires-Dist: polars (>=0.20.0)
Requires-Dist: pydantic (>=2.0.0)
Requires-Dist: pytest (>=7.0) ; extra == "tests"
Requires-Dist: pytest (>=8.4.1,<9.0.0)
Requires-Dist: pytest-benchmark (>=4.0) ; extra == "tests"
Requires-Dist: pytest-cov (>=4.1) ; extra == "tests"
Requires-Dist: pyyaml (>=6.0)
Requires-Dist: rich (>=13.0.0)
Requires-Dist: typer (>=0.9.0)
Requires-Dist: uuid (>=1.30)
Project-URL: Homepage, https://github.com/your-org/EndoFactory
Project-URL: Issues, https://github.com/your-org/EndoFactory/issues
Project-URL: Repository, https://github.com/your-org/EndoFactory
